nmfspalettepy/__init__.py
nmfspalettepy/palettes.py
nmfspalettepy-0.1.21.dist-info/LICENSE.md
nmfspalettepy-0.1.21.dist-info/METADATA
nmfspalettepy-0.1.21.dist-info/WHEEL
nmfspalettepy-0.1.21.dist-info/top_level.txt
nmfspalettepy-0.1.21.dist-info/RECORD
