Metadata-Version: 2.1
Name: nmfspalettepy
Version: 0.1.21
Summary: NMFS color palettes handling library
Author: Michael Akridge
Classifier: Intended Audience :: Developers
Classifier: Programming Language :: Python :: 3
Classifier: Programming Language :: Python :: 3.7
Classifier: Programming Language :: Python :: 3.8
Classifier: Programming Language :: Python :: 3.9
License-File: LICENSE.md
Requires-Dist: numpy
Requires-Dist: matplotlib
